gibooru/__init__.py
gibooru/booru.py
gibooru/danbooru.py
gibooru/gelbooru.py
gibooru-1.0.2.dist-info/LICENSE
gibooru-1.0.2.dist-info/METADATA
gibooru-1.0.2.dist-info/WHEEL
gibooru-1.0.2.dist-info/top_level.txt
gibooru-1.0.2.dist-info/RECORD
